<colors><color value="桜色" name="#fef4f4" style="background-color: rgb(254, 244, 244);">桜色 #fef4f4</color>
<color value="薄桜" name="#fdeff2" style="background-color: rgb(253, 239, 242);">薄桜 #fdeff2</color><color value="桜鼠" name="#e9dfe5" style="background-color: rgb(233, 223, 229);">桜鼠 #e9dfe5</color><color value="鴇鼠" name="#e4d2d8" style="background-color: rgb(228, 210, 216);">鴇鼠 #e4d2d8</color><color value="虹色" name="#f6bfbc" style="background-color: rgb(246, 191, 188);">虹色 #f6bfbc</color><color value="珊瑚色" name="#f5b1aa" style="background-color: rgb(245, 177, 170);">珊瑚色 #f5b1aa</color><color value="一斤染" name="#f5b199" style="background-color: rgb(245, 177, 153);">一斤染 #f5b199</color><color value="宍色" name="#efab93" style="background-color: rgb(239, 171, 147);">宍色 #efab93</color><color value="紅梅色" name="#f2a0a1" style="background-color: rgb(242, 160, 161);">紅梅色 #f2a0a1</color><color value="薄紅" name="#f0908d" style="background-color: rgb(240, 144, 141);">薄紅 #f0908d</color><color value="甚三紅" name="#ee827c" style="background-color: rgb(238, 130, 124);">甚三紅 #ee827c</color><color value="桃色" name="#f09199" style="background-color: rgb(240, 145, 153);">桃色 #f09199</color><color value="鴇色" name="#f4b3c2" style="background-color: rgb(244, 179, 194);">鴇色 #f4b3c2</color><color value="撫子色" name="#eebbcb" style="background-color: rgb(238, 187, 203);">撫子色 #eebbcb</color><color value="灰梅" name="#e8d3c7" style="background-color: rgb(232, 211, 199);">灰梅 #e8d3c7</color><color value="灰桜" name="#e8d3d1" style="background-color: rgb(232, 211, 209);">灰桜 #e8d3d1</color><color value="淡紅藤" name="#e6cde3" style="background-color: rgb(230, 205, 227);">淡紅藤 #e6cde3</color><color value="石竹色" name="#e5abbe" style="background-color: rgb(229, 171, 190);">石竹色 #e5abbe</color><color value="薄紅梅" name="#e597b2" style="background-color: rgb(229, 151, 178);">薄紅梅 #e597b2</color><color value="桃花色" name="#e198b4" style="background-color: rgb(225, 152, 180);">桃花色 #e198b4</color><color value="水柿" name="#e4ab9b" style="background-color: rgb(228, 171, 155);">水柿 #e4ab9b</color><color value="ときがら茶" name="#e09e87" style="background-color: rgb(224, 158, 135);">ときがら茶 #e09e87</color><color value="退紅" name="#d69090" style="background-color: rgb(214, 144, 144);">退紅 #d69090</color><color value="薄柿" name="#d4acad" style="background-color: rgb(212, 172, 173);">薄柿 #d4acad</color><color value="長春色" name="#c97586" style="background-color: rgb(201, 117, 134);">長春色 #c97586</color><color value="梅鼠" name="#c099a0" style="background-color: rgb(192, 153, 160);">梅鼠 #c099a0</color><color value="鴇浅葱" name="#b88884" style="background-color: rgb(184, 136, 132);">鴇浅葱 #b88884</color><color value="梅染" name="#b48a76" style="background-color: rgb(180, 138, 118);">梅染 #b48a76</color><color value="蘇芳香" name="#a86965" style="background-color: rgb(168, 105, 101);">蘇芳香 #a86965</color><color value="浅蘇芳" name="#a25768" style="background-color: rgb(162, 87, 104);">浅蘇芳 #a25768</color><color value="真朱" name="#ec6d71" style="background-color: rgb(236, 109, 113);">真朱 #ec6d71</color><color value="赤紫" name="#eb6ea5" style="background-color: rgb(235, 110, 165);">赤紫 #eb6ea5</color><color value="躑躅色" name="#e95295" style="background-color: rgb(233, 82, 149);">躑躅色 #e95295</color><color value="牡丹色" name="#e7609e" style="background-color: rgb(231, 96, 158);">牡丹色 #e7609e</color><color value="今様色" name="#d0576b" style="background-color: rgb(208, 87, 107);">今様色 #d0576b</color><color value="中紅" name="#c85179" style="background-color: rgb(200, 81, 121);">中紅 #c85179</color><color value="薔薇色" name="#e9546b" style="background-color: rgb(233, 84, 107);">薔薇色 #e9546b</color><color value="韓紅" name="#e95464" style="background-color: rgb(233, 84, 100);">韓紅 #e95464</color><color value="銀朱" name="#c85554" style="background-color: rgb(200, 85, 84);">銀朱 #c85554</color><color value="赤紅" name="#c53d43" style="background-color: rgb(197, 61, 67);">赤紅 #c53d43</color><color value="紅緋" name="#e83929" style="background-color: rgb(232, 57, 41);">紅緋 #e83929</color><color value="赤" name="#e60033" style="background-color: rgb(230, 0, 51);">赤 #e60033</color><color value="猩々緋" name="#e2041b" style="background-color: rgb(226, 4, 27);">猩々緋 #e2041b</color><color value="紅" name="#d7003a" style="background-color: rgb(215, 0, 58);">紅 #d7003a</color><color value="深緋" name="#c9171e" style="background-color: rgb(201, 23, 30);">深緋 #c9171e</color><color value="緋色" name="#d3381c" style="background-color: rgb(211, 56, 28);">緋色 #d3381c</color><color value="赤丹" name="#ce5242" style="background-color: rgb(206, 82, 66);">赤丹 #ce5242</color><color value="紅赤" name="#d9333f" style="background-color: rgb(217, 51, 63);">紅赤 #d9333f</color><color value="臙脂" name="#b94047" style="background-color: rgb(185, 64, 71);">臙脂 #b94047</color><color value="朱・緋" name="#ba2636" style="background-color: rgb(186, 38, 54);">朱・緋 #ba2636</color><color value="茜色" name="#b7282e" style="background-color: rgb(183, 40, 46);">茜色 #b7282e</color><color value="紅海老茶" name="#a73836" style="background-color: rgb(167, 56, 54);">紅海老茶 #a73836</color><color value="蘇芳" name="#9e3d3f" style="background-color: rgb(158, 61, 63);">蘇芳 #9e3d3f</color><color value="真紅" name="#a22041" style="background-color: rgb(162, 32, 65);">真紅 #a22041</color><color value="濃紅" name="#a22041" style="background-color: rgb(162, 32, 65);">濃紅 #a22041</color><color value="象牙色" name="#f8f4e6" style="background-color: rgb(248, 244, 230);">象牙色 #f8f4e6</color><color value="練色" name="#ede4cd" style="background-color: rgb(237, 228, 205);">練色 #ede4cd</color><color value="灰白色" name="#e9e4d4" style="background-color: rgb(233, 228, 212);">灰白色 #e9e4d4</color><color value="蒸栗色" name="#ebe1a9" style="background-color: rgb(235, 225, 169);">蒸栗色 #ebe1a9</color><color value="女郎花" name="#f2f2b0" style="background-color: rgb(242, 242, 176);">女郎花 #f2f2b0</color><color value="枯草色" name="#e4dc8a" style="background-color: rgb(228, 220, 138);">枯草色 #e4dc8a</color><color value="淡黄" name="#f8e58c" style="background-color: rgb(248, 229, 140);">淡黄 #f8e58c</color><color value="白茶" name="#ddbb99" style="background-color: rgb(221, 187, 153);">白茶 #ddbb99</color><color value="赤白橡" name="#d7a98c" style="background-color: rgb(215, 169, 140);">赤白橡 #d7a98c</color><color value="洗柿" name="#f2c9ac" style="background-color: rgb(242, 201, 172);">洗柿 #f2c9ac</color><color value="鳥の子色" name="#fff1cf" style="background-color: rgb(255, 241, 207);">鳥の子色 #fff1cf</color><color value="蜂蜜色" name="#fddea5" style="background-color: rgb(253, 222, 165);">蜂蜜色 #fddea5</color><color value="肌色" name="#fce2c4" style="background-color: rgb(252, 226, 196);">肌色 #fce2c4</color><color value="薄卵色" name="#fde8d0" style="background-color: rgb(253, 232, 208);">薄卵色 #fde8d0</color><color value="雄黄" name="#f9c89b" style="background-color: rgb(249, 200, 155);">雄黄 #f9c89b</color><color value="洒落柿" name="#f7bd8f" style="background-color: rgb(247, 189, 143);">洒落柿 #f7bd8f</color><color value="赤香" name="#f6b894" style="background-color: rgb(246, 184, 148);">赤香 #f6b894</color><color value="砥粉色" name="#f4dda5" style="background-color: rgb(244, 221, 165);">砥粉色 #f4dda5</color><color value="肉色" name="#f1bf99" style="background-color: rgb(241, 191, 153);">肉色 #f1bf99</color><color value="人色" name="#f1bf99" style="background-color: rgb(241, 191, 153);">人色 #f1bf99</color><color value="丁子色" name="#efcd9a" style="background-color: rgb(239, 205, 154);">丁子色 #efcd9a</color><color value="香色" name="#efcd9a" style="background-color: rgb(239, 205, 154);">香色 #efcd9a</color><color value="薄香" name="#f0cfa0" style="background-color: rgb(240, 207, 160);">薄香 #f0cfa0</color><color value="浅黄" name="#edd3a1" style="background-color: rgb(237, 211, 161);">浅黄 #edd3a1</color><color value="枯色" name="#e0c38c" style="background-color: rgb(224, 195, 140);">枯色 #e0c38c</color><color value="淡香" name="#f3bf88" style="background-color: rgb(243, 191, 136);">淡香 #f3bf88</color><color value="杏色" name="#f7b977" style="background-color: rgb(247, 185, 119);">杏色 #f7b977</color><color value="東雲色" name="#f19072" style="background-color: rgb(241, 144, 114);">東雲色 #f19072</color><color value="曙色" name="#f19072" style="background-color: rgb(241, 144, 114);">曙色 #f19072</color><color value="珊瑚朱色" name="#ee836f" style="background-color: rgb(238, 131, 111);">珊瑚朱色 #ee836f</color><color value="深支子" name="#eb9b6f" style="background-color: rgb(235, 155, 111);">深支子 #eb9b6f</color><color value="纁" name="#e0815e" style="background-color: rgb(224, 129, 94);">纁 #e0815e</color><color value="浅緋" name="#df7163" style="background-color: rgb(223, 113, 99);">浅緋 #df7163</color><color value="真赭" name="#d57c6b" style="background-color: rgb(213, 124, 107);">真赭 #d57c6b</color><color value="洗朱" name="#d0826c" style="background-color: rgb(208, 130, 108);">洗朱 #d0826c</color><color value="遠州茶" name="#ca8269" style="background-color: rgb(202, 130, 105);">遠州茶 #ca8269</color><color value="紅樺色" name="#bb5548" style="background-color: rgb(187, 85, 72);">紅樺色 #bb5548</color><color value="赭" name="#ab6953" style="background-color: rgb(171, 105, 83);">赭 #ab6953</color><color value="小豆色" name="#96514d" style="background-color: rgb(150, 81, 77);">小豆色 #96514d</color><color value="枯茶" name="#8d6449" style="background-color: rgb(141, 100, 73);">枯茶 #8d6449</color><color value="飴色" name="#deb068" style="background-color: rgb(222, 176, 104);">飴色 #deb068</color><color value="駱駝色" name="#bf794e" style="background-color: rgb(191, 121, 78);">駱駝色 #bf794e</color><color value="土色" name="#bc763c" style="background-color: rgb(188, 118, 60);">土色 #bc763c</color><color value="黄唐茶" name="#b98c46" style="background-color: rgb(185, 140, 70);">黄唐茶 #b98c46</color><color value="桑染" name="#b79b5b" style="background-color: rgb(183, 155, 91);">桑染 #b79b5b</color><color value="櫨色" name="#b77b57" style="background-color: rgb(183, 123, 87);">櫨色 #b77b57</color><color value="黄橡" name="#b68d4c" style="background-color: rgb(182, 141, 76);">黄橡 #b68d4c</color><color value="丁字染" name="#ad7d4c" style="background-color: rgb(173, 125, 76);">丁字染 #ad7d4c</color><color value="香染" name="#ad7d4c" style="background-color: rgb(173, 125, 76);">香染 #ad7d4c</color><color value="枇杷茶" name="#ae7c4f" style="background-color: rgb(174, 124, 79);">枇杷茶 #ae7c4f</color><color value="芝翫茶" name="#ad7e4e" style="background-color: rgb(173, 126, 78);">芝翫茶 #ad7e4e</color><color value="焦香" name="#ae7c58" style="background-color: rgb(174, 124, 88);">焦香 #ae7c58</color><color value="胡桃色" name="#a86f4c" style="background-color: rgb(168, 111, 76);">胡桃色 #a86f4c</color><color value="渋紙色" name="#946243" style="background-color: rgb(148, 98, 67);">渋紙色 #946243</color><color value="朽葉色" name="#917347" style="background-color: rgb(145, 115, 71);">朽葉色 #917347</color><color value="桑茶" name="#956f29" style="background-color: rgb(149, 111, 41);">桑茶 #956f29</color><color value="路考茶" name="#8c7042" style="background-color: rgb(140, 112, 66);">路考茶 #8c7042</color><color value="国防色" name="#7b6c3e" style="background-color: rgb(123, 108, 62);">国防色 #7b6c3e</color><color value="伽羅色" name="#d8a373" style="background-color: rgb(216, 163, 115);">伽羅色 #d8a373</color><color value="江戸茶" name="#cd8c5c" style="background-color: rgb(205, 140, 92);">江戸茶 #cd8c5c</color><color value="樺色" name="#cd5e3c" style="background-color: rgb(205, 94, 60);">樺色 #cd5e3c</color><color value="紅鬱金" name="#cb8347" style="background-color: rgb(203, 131, 71);">紅鬱金 #cb8347</color><color value="土器色" name="#c37854" style="background-color: rgb(195, 120, 84);">土器色 #c37854</color><color value="狐色" name="#c38743" style="background-color: rgb(195, 135, 67);">狐色 #c38743</color><color value="黄土色" name="#c39143" style="background-color: rgb(195, 145, 67);">黄土色 #c39143</color><color value="琥珀色" name="#bf783a" style="background-color: rgb(191, 120, 58);">琥珀色 #bf783a</color><color value="赤茶" name="#bb5535" style="background-color: rgb(187, 85, 53);">赤茶 #bb5535</color><color value="代赭" name="#bb5520" style="background-color: rgb(187, 85, 32);">代赭 #bb5520</color><color value="煉瓦色" name="#b55233" style="background-color: rgb(181, 82, 51);">煉瓦色 #b55233</color><color value="雀茶" name="#aa4f37" style="background-color: rgb(170, 79, 55);">雀茶 #aa4f37</color><color value="団十郎茶" name="#9f563a" style="background-color: rgb(159, 86, 58);">団十郎茶 #9f563a</color><color value="柿渋色" name="#9f563a" style="background-color: rgb(159, 86, 58);">柿渋色 #9f563a</color><color value="紅鳶" name="#9a493f" style="background-color: rgb(154, 73, 63);">紅鳶 #9a493f</color><color value="灰茶" name="#98623c" style="background-color: rgb(152, 98, 60);">灰茶 #98623c</color><color value="茶色" name="#965042" style="background-color: rgb(150, 80, 66);">茶色 #965042</color><color value="檜皮色" name="#965036" style="background-color: rgb(150, 80, 54);">檜皮色 #965036</color><color value="鳶色" name="#95483f" style="background-color: rgb(149, 72, 63);">鳶色 #95483f</color><color value="柿茶" name="#954e2a" style="background-color: rgb(149, 78, 42);">柿茶 #954e2a</color><color value="弁柄色" name="#8f2e14" style="background-color: rgb(143, 46, 20);">弁柄色 #8f2e14</color><color value="赤錆色" name="#8a3319" style="background-color: rgb(138, 51, 25);">赤錆色 #8a3319</color><color value="褐色" name="#8a3b00" style="background-color: rgb(138, 59, 0);">褐色 #8a3b00</color><color value="栗梅" name="#852e19" style="background-color: rgb(133, 46, 25);">栗梅 #852e19</color><color value="紅檜皮" name="#7b4741" style="background-color: rgb(123, 71, 65);">紅檜皮 #7b4741</color><color value="海老茶" name="#773c30" style="background-color: rgb(119, 60, 48);">海老茶 #773c30</color><color value="唐茶" name="#783c1d" style="background-color: rgb(120, 60, 29);">唐茶 #783c1d</color><color value="栗色" name="#762f07" style="background-color: rgb(118, 47, 7);">栗色 #762f07</color><color value="赤銅色" name="#752100" style="background-color: rgb(117, 33, 0);">赤銅色 #752100</color><color value="錆色" name="#6c3524" style="background-color: rgb(108, 53, 36);">錆色 #6c3524</color><color value="赤褐色" name="#683f36" style="background-color: rgb(104, 63, 54);">赤褐色 #683f36</color><color value="茶褐色" name="#664032" style="background-color: rgb(102, 64, 50);">茶褐色 #664032</color><color value="栗皮茶" name="#6d3c32" style="background-color: rgb(109, 60, 50);">栗皮茶 #6d3c32</color><color value="黒茶" name="#583822" style="background-color: rgb(88, 56, 34);">黒茶 #583822</color><color value="葡萄茶" name="#6c2c2f" style="background-color: rgb(108, 44, 47);">葡萄茶 #6c2c2f</color><color value="葡萄色" name="#640125" style="background-color: rgb(100, 1, 37);">葡萄色 #640125</color><color value="萱草色" name="#f8b862" style="background-color: rgb(248, 184, 98);">萱草色 #f8b862</color><color value="柑子色" name="#f6ad49" style="background-color: rgb(246, 173, 73);">柑子色 #f6ad49</color><color value="金茶" name="#f39800" style="background-color: rgb(243, 152, 0);">金茶 #f39800</color><color value="蜜柑色" name="#f08300" style="background-color: rgb(240, 131, 0);">蜜柑色 #f08300</color><color value="鉛丹色" name="#ec6d51" style="background-color: rgb(236, 109, 81);">鉛丹色 #ec6d51</color><color value="黄丹" name="#ee7948" style="background-color: rgb(238, 121, 72);">黄丹 #ee7948</color><color value="柿色" name="#ed6d3d" style="background-color: rgb(237, 109, 61);">柿色 #ed6d3d</color><color value="黄赤" name="#ec6800" style="background-color: rgb(236, 104, 0);">黄赤 #ec6800</color><color value="人参色" name="#ec6800" style="background-color: rgb(236, 104, 0);">人参色 #ec6800</color><color value="橙色" name="#ee7800" style="background-color: rgb(238, 120, 0);">橙色 #ee7800</color><color value="照柿" name="#eb6238" style="background-color: rgb(235, 98, 56);">照柿 #eb6238</color><color value="赤橙" name="#ea5506" style="background-color: rgb(234, 85, 6);">赤橙 #ea5506</color><color value="金赤" name="#ea5506" style="background-color: rgb(234, 85, 6);">金赤 #ea5506</color><color value="朱色" name="#eb6101" style="background-color: rgb(235, 97, 1);">朱色 #eb6101</color><color value="小麦色" name="#e49e61" style="background-color: rgb(228, 158, 97);">小麦色 #e49e61</color><color value="丹色" name="#e45e32" style="background-color: rgb(228, 94, 50);">丹色 #e45e32</color><color value="黄茶" name="#e17b34" style="background-color: rgb(225, 123, 52);">黄茶 #e17b34</color><color value="肉桂色" name="#dd7a56" style="background-color: rgb(221, 122, 86);">肉桂色 #dd7a56</color><color value="赤朽葉色" name="#db8449" style="background-color: rgb(219, 132, 73);">赤朽葉色 #db8449</color><color value="黄櫨染" name="#d66a35" style="background-color: rgb(214, 106, 53);">黄櫨染 #d66a35</color><color value="蒲公英色" name="#ffd900" style="background-color: rgb(255, 217, 0);">蒲公英色 #ffd900</color><color value="黄色" name="#ffd900" style="background-color: rgb(255, 217, 0);">黄色 #ffd900</color><color value="中黄" name="#ffea00" style="background-color: rgb(255, 234, 0);">中黄 #ffea00</color><color value="菜の花色" name="#ffec47" style="background-color: rgb(255, 236, 71);">菜の花色 #ffec47</color><color value="黄檗色" name="#fef263" style="background-color: rgb(254, 242, 99);">黄檗色 #fef263</color><color value="卵色" name="#fcd575" style="background-color: rgb(252, 213, 117);">卵色 #fcd575</color><color value="花葉色" name="#fbd26b" style="background-color: rgb(251, 210, 107);">花葉色 #fbd26b</color><color value="刈安色" name="#f5e56b" style="background-color: rgb(245, 229, 107);">刈安色 #f5e56b</color><color value="玉蜀黍色" name="#eec362" style="background-color: rgb(238, 195, 98);">玉蜀黍色 #eec362</color><color value="金糸雀色" name="#ebd842" style="background-color: rgb(235, 216, 66);">金糸雀色 #ebd842</color><color value="黄支子色" name="#ffdb4f" style="background-color: rgb(255, 219, 79);">黄支子色 #ffdb4f</color><color value="支子色" name="#fbca4d" style="background-color: rgb(251, 202, 77);">支子色 #fbca4d</color><color value="向日葵色" name="#fcc800" style="background-color: rgb(252, 200, 0);">向日葵色 #fcc800</color><color value="山吹色" name="#f8b500" style="background-color: rgb(248, 181, 0);">山吹色 #f8b500</color><color value="鬱金色" name="#fabf14" style="background-color: rgb(250, 191, 20);">鬱金色 #fabf14</color><color value="藤黄" name="#f7c114" style="background-color: rgb(247, 193, 20);">藤黄 #f7c114</color><color value="金色" name="#e6b422" style="background-color: rgb(230, 180, 34);">金色 #e6b422</color><color value="黄金" name="#e6b422" style="background-color: rgb(230, 180, 34);">黄金 #e6b422</color><color value="櫨染" name="#d9a62e" style="background-color: rgb(217, 166, 46);">櫨染 #d9a62e</color><color value="黄朽葉色" name="#d3a243" style="background-color: rgb(211, 162, 67);">黄朽葉色 #d3a243</color><color value="山吹茶" name="#c89932" style="background-color: rgb(200, 153, 50);">山吹茶 #c89932</color><color value="芥子色" name="#d0af4c" style="background-color: rgb(208, 175, 76);">芥子色 #d0af4c</color><color value="豆がら茶" name="#8b968d" style="background-color: rgb(139, 150, 141);">豆がら茶 #8b968d</color><color value="麹塵" name="#6e7955" style="background-color: rgb(110, 121, 85);">麹塵 #6e7955</color><color value="山鳩色" name="#767c6b" style="background-color: rgb(118, 124, 107);">山鳩色 #767c6b</color><color value="利休鼠" name="#888e7e" style="background-color: rgb(136, 142, 126);">利休鼠 #888e7e</color><color value="海松茶" name="#5a544b" style="background-color: rgb(90, 84, 75);">海松茶 #5a544b</color><color value="藍海松茶" name="#56564b" style="background-color: rgb(86, 86, 75);">藍海松茶 #56564b</color><color value="藍媚茶" name="#555647" style="background-color: rgb(85, 86, 71);">藍媚茶 #555647</color><color value="千歳茶" name="#494a41" style="background-color: rgb(73, 74, 65);">千歳茶 #494a41</color><color value="岩井茶" name="#6b6f59" style="background-color: rgb(107, 111, 89);">岩井茶 #6b6f59</color><color value="仙斎茶" name="#474b42" style="background-color: rgb(71, 75, 66);">仙斎茶 #474b42</color><color value="黒緑" name="#333631" style="background-color: rgb(51, 54, 49);">黒緑 #333631</color><color value="柳煤竹" name="#5b6356" style="background-color: rgb(91, 99, 86);">柳煤竹 #5b6356</color><color value="樺茶色" name="#726250" style="background-color: rgb(114, 98, 80);">樺茶色 #726250</color><color value="空五倍子色" name="#9d896c" style="background-color: rgb(157, 137, 108);">空五倍子色 #9d896c</color><color value="生壁色" name="#94846a" style="background-color: rgb(148, 132, 106);">生壁色 #94846a</color><color value="肥後煤竹" name="#897858" style="background-color: rgb(137, 120, 88);">肥後煤竹 #897858</color><color value="媚茶" name="#716246" style="background-color: rgb(113, 98, 70);">媚茶 #716246</color><color value="白橡" name="#cbb994" style="background-color: rgb(203, 185, 148);">白橡 #cbb994</color><color value="亜麻色" name="#d6c6af" style="background-color: rgb(214, 198, 175);">亜麻色 #d6c6af</color><color value="榛色" name="#bfa46f" style="background-color: rgb(191, 164, 111);">榛色 #bfa46f</color><color value="灰汁色" name="#9e9478" style="background-color: rgb(158, 148, 120);">灰汁色 #9e9478</color><color value="利休茶" name="#a59564" style="background-color: rgb(165, 149, 100);">利休茶 #a59564</color><color value="鶯茶" name="#715c1f" style="background-color: rgb(113, 92, 31);">鶯茶 #715c1f</color><color value="木蘭色" name="#c7b370" style="background-color: rgb(199, 179, 112);">木蘭色 #c7b370</color><color value="砂色" name="#dcd3b2" style="background-color: rgb(220, 211, 178);">砂色 #dcd3b2</color><color value="油色" name="#a19361" style="background-color: rgb(161, 147, 97);">油色 #a19361</color><color value="利休色" name="#8f8667" style="background-color: rgb(143, 134, 103);">利休色 #8f8667</color><color value="梅幸茶" name="#887938" style="background-color: rgb(136, 121, 56);">梅幸茶 #887938</color><color value="璃寛茶" name="#6a5d21" style="background-color: rgb(106, 93, 33);">璃寛茶 #6a5d21</color><color value="黄海松茶" name="#918754" style="background-color: rgb(145, 135, 84);">黄海松茶 #918754</color><color value="菜種油色" name="#a69425" style="background-color: rgb(166, 148, 37);">菜種油色 #a69425</color><color value="青朽葉" name="#ada250" style="background-color: rgb(173, 162, 80);">青朽葉 #ada250</color><color value="根岸色" name="#938b4b" style="background-color: rgb(147, 139, 75);">根岸色 #938b4b</color><color value="鶸茶" name="#8c8861" style="background-color: rgb(140, 136, 97);">鶸茶 #8c8861</color><color value="柳茶" name="#a1a46d" style="background-color: rgb(161, 164, 109);">柳茶 #a1a46d</color><color value="海松色" name="#726d40" style="background-color: rgb(114, 109, 64);">海松色 #726d40</color><color value="鶯色" name="#928c36" style="background-color: rgb(146, 140, 54);">鶯色 #928c36</color><color value="緑黄色" name="#dccb18" style="background-color: rgb(220, 203, 24);">緑黄色 #dccb18</color><color value="鶸色" name="#d7cf3a" style="background-color: rgb(215, 207, 58);">鶸色 #d7cf3a</color><color value="抹茶色" name="#c5c56a" style="background-color: rgb(197, 197, 106);">抹茶色 #c5c56a</color><color value="若草色" name="#c3d825" style="background-color: rgb(195, 216, 37);">若草色 #c3d825</color><color value="黄緑" name="#b8d200" style="background-color: rgb(184, 210, 0);">黄緑 #b8d200</color><color value="若芽色" name="#e0ebaf" style="background-color: rgb(224, 235, 175);">若芽色 #e0ebaf</color><color value="若菜色" name="#d8e698" style="background-color: rgb(216, 230, 152);">若菜色 #d8e698</color><color value="若苗色" name="#c7dc68" style="background-color: rgb(199, 220, 104);">若苗色 #c7dc68</color><color value="青丹" name="#99ab4e" style="background-color: rgb(153, 171, 78);">青丹 #99ab4e</color><color value="草色" name="#7b8d42" style="background-color: rgb(123, 141, 66);">草色 #7b8d42</color><color value="苔色" name="#69821b" style="background-color: rgb(105, 130, 27);">苔色 #69821b</color><color value="萌黄" name="#aacf53" style="background-color: rgb(170, 207, 83);">萌黄 #aacf53</color><color value="苗色" name="#b0ca71" style="background-color: rgb(176, 202, 113);">苗色 #b0ca71</color><color value="若葉色" name="#b9d08b" style="background-color: rgb(185, 208, 139);">若葉色 #b9d08b</color><color value="松葉色" name="#839b5c" style="background-color: rgb(131, 155, 92);">松葉色 #839b5c</color><color value="夏虫色" name="#cee4ae" style="background-color: rgb(206, 228, 174);">夏虫色 #cee4ae</color><color value="鶸萌黄" name="#82ae46" style="background-color: rgb(130, 174, 70);">鶸萌黄 #82ae46</color><color value="柳色" name="#a8c97f" style="background-color: rgb(168, 201, 127);">柳色 #a8c97f</color><color value="青白橡" name="#9ba88d" style="background-color: rgb(155, 168, 141);">青白橡 #9ba88d</color><color value="柳鼠" name="#c8d5bb" style="background-color: rgb(200, 213, 187);">柳鼠 #c8d5bb</color><color value="裏葉柳" name="#c1d8ac" style="background-color: rgb(193, 216, 172);">裏葉柳 #c1d8ac</color><color value="山葵色" name="#a8bf93" style="background-color: rgb(168, 191, 147);">山葵色 #a8bf93</color><color value="老竹色" name="#769164" style="background-color: rgb(118, 145, 100);">老竹色 #769164</color><color value="白緑" name="#d6e9ca" style="background-color: rgb(214, 233, 202);">白緑 #d6e9ca</color><color value="淡萌黄" name="#93ca76" style="background-color: rgb(147, 202, 118);">淡萌黄 #93ca76</color><color value="柳染" name="#93b881" style="background-color: rgb(147, 184, 129);">柳染 #93b881</color><color value="薄萌葱" name="#badcad" style="background-color: rgb(186, 220, 173);">薄萌葱 #badcad</color><color value="深川鼠" name="#97a791" style="background-color: rgb(151, 167, 145);">深川鼠 #97a791</color><color value="若緑" name="#98d98e" style="background-color: rgb(152, 217, 142);">若緑 #98d98e</color><color value="浅緑" name="#88cb7f" style="background-color: rgb(136, 203, 127);">浅緑 #88cb7f</color><color value="薄緑" name="#69b076" style="background-color: rgb(105, 176, 118);">薄緑 #69b076</color><color value="青鈍" name="#6b7b6e" style="background-color: rgb(107, 123, 110);">青鈍 #6b7b6e</color><color value="青磁鼠" name="#bed2c3" style="background-color: rgb(190, 210, 195);">青磁鼠 #bed2c3</color><color value="薄青" name="#93b69c" style="background-color: rgb(147, 182, 156);">薄青 #93b69c</color><color value="錆青磁" name="#a6c8b2" style="background-color: rgb(166, 200, 178);">錆青磁 #a6c8b2</color><color value="緑青色" name="#47885e" style="background-color: rgb(71, 136, 94);">緑青色 #47885e</color><color value="千歳緑" name="#316745" style="background-color: rgb(49, 103, 69);">千歳緑 #316745</color><color value="若竹色" name="#68be8d" style="background-color: rgb(104, 190, 141);">若竹色 #68be8d</color><color value="緑" name="#3eb370" style="background-color: rgb(62, 179, 112);">緑 #3eb370</color><color value="常磐色" name="#007b43" style="background-color: rgb(0, 123, 67);">常磐色 #007b43</color><color value="千草鼠" name="#bed3ca" style="background-color: rgb(190, 211, 202);">千草鼠 #bed3ca</color><color value="千草色" name="#92b5a9" style="background-color: rgb(146, 181, 169);">千草色 #92b5a9</color><color value="青磁色" name="#7ebea5" style="background-color: rgb(126, 190, 165);">青磁色 #7ebea5</color><color value="青竹色" name="#7ebeab" style="background-color: rgb(126, 190, 171);">青竹色 #7ebeab</color><color value="常磐緑" name="#028760" style="background-color: rgb(2, 135, 96);">常磐緑 #028760</color><color value="木賊色" name="#3b7960" style="background-color: rgb(59, 121, 96);">木賊色 #3b7960</color><color value="天鵞絨" name="#2f5d50" style="background-color: rgb(47, 93, 80);">天鵞絨 #2f5d50</color><color value="虫襖" name="#3a5b52" style="background-color: rgb(58, 91, 82);">虫襖 #3a5b52</color><color value="革色" name="#475950" style="background-color: rgb(71, 89, 80);">革色 #475950</color><color value="深緑" name="#00552e" style="background-color: rgb(0, 85, 46);">深緑 #00552e</color><color value="鉄色" name="#005243" style="background-color: rgb(0, 82, 67);">鉄色 #005243</color><color value="萌葱色" name="#006e54" style="background-color: rgb(0, 110, 84);">萌葱色 #006e54</color><color value="花緑青" name="#00a381" style="background-color: rgb(0, 163, 129);">花緑青 #00a381</color><color value="翡翠色" name="#38b48b" style="background-color: rgb(56, 180, 139);">翡翠色 #38b48b</color><color value="青緑" name="#00a497" style="background-color: rgb(0, 164, 151);">青緑 #00a497</color><color value="水浅葱" name="#80aba9" style="background-color: rgb(128, 171, 169);">水浅葱 #80aba9</color><color value="錆浅葱" name="#5c9291" style="background-color: rgb(92, 146, 145);">錆浅葱 #5c9291</color><color value="青碧" name="#478384" style="background-color: rgb(71, 131, 132);">青碧 #478384</color><color value="御召茶" name="#43676b" style="background-color: rgb(67, 103, 107);">御召茶 #43676b</color><color value="湊鼠" name="#80989b" style="background-color: rgb(128, 152, 155);">湊鼠 #80989b</color><color value="高麗納戸" name="#2c4f54" style="background-color: rgb(44, 79, 84);">高麗納戸 #2c4f54</color><color value="百入茶" name="#1f3134" style="background-color: rgb(31, 49, 52);">百入茶 #1f3134</color><color value="錆鼠" name="#47585c" style="background-color: rgb(71, 88, 92);">錆鼠 #47585c</color><color value="錆鉄御納戸" name="#485859" style="background-color: rgb(72, 88, 89);">錆鉄御納戸 #485859</color><color value="藍鼠" name="#6c848d" style="background-color: rgb(108, 132, 141);">藍鼠 #6c848d</color><color value="錆御納戸" name="#53727d" style="background-color: rgb(83, 114, 125);">錆御納戸 #53727d</color><color value="舛花色" name="#5b7e91" style="background-color: rgb(91, 126, 145);">舛花色 #5b7e91</color><color value="熨斗目花色" name="#426579" style="background-color: rgb(66, 101, 121);">熨斗目花色 #426579</color><color value="御召御納戸" name="#4c6473" style="background-color: rgb(76, 100, 115);">御召御納戸 #4c6473</color><color value="鉄御納戸" name="#455765" style="background-color: rgb(69, 87, 101);">鉄御納戸 #455765</color><color value="紺鼠" name="#44617b" style="background-color: rgb(68, 97, 123);">紺鼠 #44617b</color><color value="藍鉄" name="#393f4c" style="background-color: rgb(57, 63, 76);">藍鉄 #393f4c</color><color value="青褐" name="#393e4f" style="background-color: rgb(57, 62, 79);">青褐 #393e4f</color><color value="褐返" name="#203744" style="background-color: rgb(32, 55, 68);">褐返 #203744</color><color value="褐色" name="#4d4c61" style="background-color: rgb(77, 76, 97);">褐色 #4d4c61</color><color value="月白" name="#eaf4fc" style="background-color: rgb(234, 244, 252);">月白 #eaf4fc</color><color value="白菫色" name="#eaedf7" style="background-color: rgb(234, 237, 247);">白菫色 #eaedf7</color><color value="白花色" name="#e8ecef" style="background-color: rgb(232, 236, 239);">白花色 #e8ecef</color><color value="藍白" name="#ebf6f7" style="background-color: rgb(235, 246, 247);">藍白 #ebf6f7</color><color value="白藍" name="#c1e4e9" style="background-color: rgb(193, 228, 233);">白藍 #c1e4e9</color><color value="水色" name="#bce2e8" style="background-color: rgb(188, 226, 232);">水色 #bce2e8</color><color value="瓶覗" name="#a2d7dd" style="background-color: rgb(162, 215, 221);">瓶覗 #a2d7dd</color><color value="秘色色" name="#abced8" style="background-color: rgb(171, 206, 216);">秘色色 #abced8</color><color value="空色" name="#a0d8ef" style="background-color: rgb(160, 216, 239);">空色 #a0d8ef</color><color value="勿忘草色" name="#89c3eb" style="background-color: rgb(137, 195, 235);">勿忘草色 #89c3eb</color><color value="青藤色" name="#84a2d4" style="background-color: rgb(132, 162, 212);">青藤色 #84a2d4</color><color value="白群" name="#83ccd2" style="background-color: rgb(131, 204, 210);">白群 #83ccd2</color><color value="浅縹" name="#84b9cb" style="background-color: rgb(132, 185, 203);">浅縹 #84b9cb</color><color value="薄花色" name="#698aab" style="background-color: rgb(105, 138, 171);">薄花色 #698aab</color><color value="納戸色" name="#008899" style="background-color: rgb(0, 136, 153);">納戸色 #008899</color><color value="浅葱色" name="#00a3af" style="background-color: rgb(0, 163, 175);">浅葱色 #00a3af</color><color value="花浅葱" name="#2a83a2" style="background-color: rgb(42, 131, 162);">花浅葱 #2a83a2</color><color value="新橋色" name="#59b9c6" style="background-color: rgb(89, 185, 198);">新橋色 #59b9c6</color><color value="天色" name="#2ca9e1" style="background-color: rgb(44, 169, 225);">天色 #2ca9e1</color><color value="露草色" name="#38a1db" style="background-color: rgb(56, 161, 219);">露草色 #38a1db</color><color value="青" name="#0095d9" style="background-color: rgb(0, 149, 217);">青 #0095d9</color><color value="薄藍" name="#0094c8" style="background-color: rgb(0, 148, 200);">薄藍 #0094c8</color><color value="縹色" name="#2792c3" style="background-color: rgb(39, 146, 195);">縹色 #2792c3</color><color value="紺碧" name="#007bbb" style="background-color: rgb(0, 123, 187);">紺碧 #007bbb</color><color value="薄群青" name="#5383c3" style="background-color: rgb(83, 131, 195);">薄群青 #5383c3</color><color value="薄花桜" name="#5a79ba" style="background-color: rgb(90, 121, 186);">薄花桜 #5a79ba</color><color value="群青色" name="#4c6cb3" style="background-color: rgb(76, 108, 179);">群青色 #4c6cb3</color><color value="杜若色" name="#3e62ad" style="background-color: rgb(62, 98, 173);">杜若色 #3e62ad</color><color value="瑠璃色" name="#1e50a2" style="background-color: rgb(30, 80, 162);">瑠璃色 #1e50a2</color><color value="薄縹" name="#507ea4" style="background-color: rgb(80, 126, 164);">薄縹 #507ea4</color><color value="瑠璃紺" name="#19448e" style="background-color: rgb(25, 68, 142);">瑠璃紺 #19448e</color><color value="紺瑠璃" name="#164a84" style="background-color: rgb(22, 74, 132);">紺瑠璃 #164a84</color><color value="藍色" name="#165e83" style="background-color: rgb(22, 94, 131);">藍色 #165e83</color><color value="青藍" name="#274a78" style="background-color: rgb(39, 74, 120);">青藍 #274a78</color><color value="深縹" name="#2a4073" style="background-color: rgb(42, 64, 115);">深縹 #2a4073</color><color value="紺色" name="#223a70" style="background-color: rgb(34, 58, 112);">紺色 #223a70</color><color value="紺青" name="#192f60" style="background-color: rgb(25, 47, 96);">紺青 #192f60</color><color value="留紺" name="#1c305c" style="background-color: rgb(28, 48, 92);">留紺 #1c305c</color><color value="濃藍" name="#0f2350" style="background-color: rgb(15, 35, 80);">濃藍 #0f2350</color><color value="鉄紺" name="#17184b" style="background-color: rgb(23, 24, 75);">鉄紺 #17184b</color><color value="漆黒" name="#0d0015" style="background-color: rgb(13, 0, 21);">漆黒 #0d0015</color><color value="淡藤色" name="#bbc8e6" style="background-color: rgb(187, 200, 230);">淡藤色 #bbc8e6</color><color value="藤色" name="#bbbcde" style="background-color: rgb(187, 188, 222);">藤色 #bbbcde</color><color value="紅掛空色" name="#8491c3" style="background-color: rgb(132, 145, 195);">紅掛空色 #8491c3</color><color value="紅碧" name="#8491c3" style="background-color: rgb(132, 145, 195);">紅碧 #8491c3</color><color value="紺桔梗" name="#4d5aaf" style="background-color: rgb(77, 90, 175);">紺桔梗 #4d5aaf</color><color value="花色" name="#4d5aaf" style="background-color: rgb(77, 90, 175);">花色 #4d5aaf</color><color value="紺藍" name="#4a488e" style="background-color: rgb(74, 72, 142);">紺藍 #4a488e</color><color value="紅桔梗" name="#4d4398" style="background-color: rgb(77, 67, 152);">紅桔梗 #4d4398</color><color value="桔梗色" name="#5654a2" style="background-color: rgb(86, 84, 162);">桔梗色 #5654a2</color><color value="藤納戸" name="#706caa" style="background-color: rgb(112, 108, 170);">藤納戸 #706caa</color><color value="紅掛花色" name="#68699b" style="background-color: rgb(104, 105, 155);">紅掛花色 #68699b</color><color value="紫苑色" name="#867ba9" style="background-color: rgb(134, 123, 169);">紫苑色 #867ba9</color><color value="白藤色" name="#dbd0e6" style="background-color: rgb(219, 208, 230);">白藤色 #dbd0e6</color><color value="藤紫" name="#a59aca" style="background-color: rgb(165, 154, 202);">藤紫 #a59aca</color><color value="菫色" name="#7058a3" style="background-color: rgb(112, 88, 163);">菫色 #7058a3</color><color value="青紫" name="#674598" style="background-color: rgb(103, 69, 152);">青紫 #674598</color><color value="菖蒲色" name="#674196" style="background-color: rgb(103, 65, 150);">菖蒲色 #674196</color><color value="竜胆色" name="#9079ad" style="background-color: rgb(144, 121, 173);">竜胆色 #9079ad</color><color value="江戸紫" name="#745399" style="background-color: rgb(116, 83, 153);">江戸紫 #745399</color><color value="本紫" name="#65318e" style="background-color: rgb(101, 49, 142);">本紫 #65318e</color><color value="葡萄色" name="#522f60" style="background-color: rgb(82, 47, 96);">葡萄色 #522f60</color><color value="深紫" name="#493759" style="background-color: rgb(73, 55, 89);">深紫 #493759</color><color value="紫黒" name="#2e2930" style="background-color: rgb(46, 41, 48);">紫黒 #2e2930</color><color value="紫" name="#884898" style="background-color: rgb(136, 72, 152);">紫 #884898</color><color value="薄葡萄" name="#c0a2c7" style="background-color: rgb(192, 162, 199);">薄葡萄 #c0a2c7</color><color value="紫紺" name="#460e44" style="background-color: rgb(70, 14, 68);">紫紺 #460e44</color><color value="暗紅色" name="#74325c" style="background-color: rgb(116, 50, 92);">暗紅色 #74325c</color><color value="桑の実色" name="#55295b" style="background-color: rgb(85, 41, 91);">桑の実色 #55295b</color><color value="古代紫" name="#895b8a" style="background-color: rgb(137, 91, 138);">古代紫 #895b8a</color><color value="茄子紺" name="#824880" style="background-color: rgb(130, 72, 128);">茄子紺 #824880</color><color value="二藍" name="#915c8b" style="background-color: rgb(145, 92, 139);">二藍 #915c8b</color><color value="京紫" name="#9d5b8b" style="background-color: rgb(157, 91, 139);">京紫 #9d5b8b</color><color value="蒲葡" name="#7a4171" style="background-color: rgb(122, 65, 113);">蒲葡 #7a4171</color><color value="若紫" name="#bc64a4" style="background-color: rgb(188, 100, 164);">若紫 #bc64a4</color><color value="紅紫" name="#b44c97" style="background-color: rgb(180, 76, 151);">紅紫 #b44c97</color><color value="梅紫" name="#aa4c8f" style="background-color: rgb(170, 76, 143);">梅紫 #aa4c8f</color><color value="菖蒲色" name="#cc7eb1" style="background-color: rgb(204, 126, 177);">菖蒲色 #cc7eb1</color><color value="紅藤色" name="#cca6bf" style="background-color: rgb(204, 166, 191);">紅藤色 #cca6bf</color><color value="浅紫" name="#c4a3bf" style="background-color: rgb(196, 163, 191);">浅紫 #c4a3bf</color><color value="紫水晶" name="#e7e7eb" style="background-color: rgb(231, 231, 235);">紫水晶 #e7e7eb</color><color value="薄梅鼠" name="#dcd6d9" style="background-color: rgb(220, 214, 217);">薄梅鼠 #dcd6d9</color><color value="暁鼠" name="#d3cfd9" style="background-color: rgb(211, 207, 217);">暁鼠 #d3cfd9</color><color value="牡丹鼠" name="#d3ccd6" style="background-color: rgb(211, 204, 214);">牡丹鼠 #d3ccd6</color><color value="霞色" name="#c8c2c6" style="background-color: rgb(200, 194, 198);">霞色 #c8c2c6</color><color value="藤鼠" name="#a6a5c4" style="background-color: rgb(166, 165, 196);">藤鼠 #a6a5c4</color><color value="半色" name="#a69abd" style="background-color: rgb(166, 154, 189);">半色 #a69abd</color><color value="薄色" name="#a89dac" style="background-color: rgb(168, 157, 172);">薄色 #a89dac</color><color value="薄鼠" name="#9790a4" style="background-color: rgb(151, 144, 164);">薄鼠 #9790a4</color><color value="鳩羽鼠" name="#9e8b8e" style="background-color: rgb(158, 139, 142);">鳩羽鼠 #9e8b8e</color><color value="鳩羽色" name="#95859c" style="background-color: rgb(149, 133, 156);">鳩羽色 #95859c</color><color value="桔梗鼠" name="#95949a" style="background-color: rgb(149, 148, 154);">桔梗鼠 #95949a</color><color value="紫鼠" name="#71686c" style="background-color: rgb(113, 104, 108);">紫鼠 #71686c</color><color value="葡萄鼠" name="#705b67" style="background-color: rgb(112, 91, 103);">葡萄鼠 #705b67</color><color value="濃色" name="#634950" style="background-color: rgb(99, 73, 80);">濃色 #634950</color><color value="紫鳶" name="#5f414b" style="background-color: rgb(95, 65, 75);">紫鳶 #5f414b</color><color value="濃鼠" name="#4f455c" style="background-color: rgb(79, 69, 92);">濃鼠 #4f455c</color><color value="藤煤竹" name="#5a5359" style="background-color: rgb(90, 83, 89);">藤煤竹 #5a5359</color><color value="滅紫" name="#594255" style="background-color: rgb(89, 66, 85);">滅紫 #594255</color><color value="紅消鼠" name="#524748" style="background-color: rgb(82, 71, 72);">紅消鼠 #524748</color><color value="似せ紫" name="#513743" style="background-color: rgb(81, 55, 67);">似せ紫 #513743</color><color value="灰黄緑" name="#e6eae3" style="background-color: rgb(230, 234, 227);">灰黄緑 #e6eae3</color><color value="蕎麦切色" name="#d4dcd6" style="background-color: rgb(212, 220, 214);">蕎麦切色 #d4dcd6</color><color value="薄雲鼠" name="#d4dcda" style="background-color: rgb(212, 220, 218);">薄雲鼠 #d4dcda</color><color value="枯野色" name="#d3cbc6" style="background-color: rgb(211, 203, 198);">枯野色 #d3cbc6</color><color value="潤色" name="#c8c2be" style="background-color: rgb(200, 194, 190);">潤色 #c8c2be</color><color value="利休白茶" name="#b3ada0" style="background-color: rgb(179, 173, 160);">利休白茶 #b3ada0</color><color value="茶鼠" name="#a99e93" style="background-color: rgb(169, 158, 147);">茶鼠 #a99e93</color><color value="胡桃染" name="#a58f86" style="background-color: rgb(165, 143, 134);">胡桃染 #a58f86</color><color value="江戸鼠" name="#928178" style="background-color: rgb(146, 129, 120);">江戸鼠 #928178</color><color value="煤色" name="#887f7a" style="background-color: rgb(136, 127, 122);">煤色 #887f7a</color><color value="丁子茶" name="#b4866b" style="background-color: rgb(180, 134, 107);">丁子茶 #b4866b</color><color value="柴染" name="#b28c6e" style="background-color: rgb(178, 140, 110);">柴染 #b28c6e</color><color value="宗伝唐茶" name="#a16d5d" style="background-color: rgb(161, 109, 93);">宗伝唐茶 #a16d5d</color><color value="砺茶" name="#9f6f55" style="background-color: rgb(159, 111, 85);">砺茶 #9f6f55</color><color value="煎茶色" name="#8c6450" style="background-color: rgb(140, 100, 80);">煎茶色 #8c6450</color><color value="銀煤竹" name="#856859" style="background-color: rgb(133, 104, 89);">銀煤竹 #856859</color><color value="黄枯茶" name="#765c47" style="background-color: rgb(118, 92, 71);">黄枯茶 #765c47</color><color value="煤竹色" name="#6f514c" style="background-color: rgb(111, 81, 76);">煤竹色 #6f514c</color><color value="焦茶" name="#6f4b3e" style="background-color: rgb(111, 75, 62);">焦茶 #6f4b3e</color><color value="黒橡" name="#544a47" style="background-color: rgb(84, 74, 71);">黒橡 #544a47</color><color value="憲法色" name="#543f32" style="background-color: rgb(84, 63, 50);">憲法色 #543f32</color><color value="涅色" name="#554738" style="background-color: rgb(85, 71, 56);">涅色 #554738</color><color value="檳榔子染" name="#433d3c" style="background-color: rgb(67, 61, 60);">檳榔子染 #433d3c</color><color value="黒鳶" name="#432f2f" style="background-color: rgb(67, 47, 47);">黒鳶 #432f2f</color><color value="赤墨" name="#3f312b" style="background-color: rgb(63, 49, 43);">赤墨 #3f312b</color><color value="黒紅" name="#302833" style="background-color: rgb(48, 40, 51);">黒紅 #302833</color><color value="白" name="#ffffff" style="background-color: rgb(255, 255, 255);">白 #ffffff</color><color value="胡粉色" name="#fffffc" style="background-color: rgb(255, 255, 252);">胡粉色 #fffffc</color><color value="卯の花色" name="#f7fcfe" style="background-color: rgb(247, 252, 254);">卯の花色 #f7fcfe</color><color value="白磁" name="#f8fbf8" style="background-color: rgb(248, 251, 248);">白磁 #f8fbf8</color><color value="生成り色" name="#fbfaf5" style="background-color: rgb(251, 250, 245);">生成り色 #fbfaf5</color><color value="乳白色" name="#f3f3f3" style="background-color: rgb(243, 243, 243);">乳白色 #f3f3f3</color><color value="白練" name="#f3f3f2" style="background-color: rgb(243, 243, 242);">白練 #f3f3f2</color><color value="素色" name="#eae5e3" style="background-color: rgb(234, 229, 227);">素色 #eae5e3</color><color value="白梅鼠" name="#e5e4e6" style="background-color: rgb(229, 228, 230);">白梅鼠 #e5e4e6</color><color value="白鼠" name="#dcdddd" style="background-color: rgb(220, 221, 221);">白鼠 #dcdddd</color><color value="絹鼠" name="#dddcd6" style="background-color: rgb(221, 220, 214);">絹鼠 #dddcd6</color><color value="灰青" name="#c0c6c9" style="background-color: rgb(192, 198, 201);">灰青 #c0c6c9</color><color value="銀鼠" name="#afafb0" style="background-color: rgb(175, 175, 176);">銀鼠 #afafb0</color><color value="薄鈍" name="#adadad" style="background-color: rgb(173, 173, 173);">薄鈍 #adadad</color><color value="薄墨色" name="#a3a3a2" style="background-color: rgb(163, 163, 162);">薄墨色 #a3a3a2</color><color value="錫色" name="#9ea1a3" style="background-color: rgb(158, 161, 163);">錫色 #9ea1a3</color><color value="素鼠" name="#9fa0a0" style="background-color: rgb(159, 160, 160);">素鼠 #9fa0a0</color><color value="鼠色" name="#949495" style="background-color: rgb(148, 148, 149);">鼠色 #949495</color><color value="源氏鼠" name="#888084" style="background-color: rgb(136, 128, 132);">源氏鼠 #888084</color><color value="灰色" name="#7d7d7d" style="background-color: rgb(125, 125, 125);">灰色 #7d7d7d</color><color value="鉛色" name="#7b7c7d" style="background-color: rgb(123, 124, 125);">鉛色 #7b7c7d</color><color value="鈍色" name="#727171" style="background-color: rgb(114, 113, 113);">鈍色 #727171</color><color value="墨" name="#595857" style="background-color: rgb(89, 88, 87);">墨 #595857</color><color value="丼鼠" name="#595455" style="background-color: rgb(89, 84, 85);">丼鼠 #595455</color><color value="消炭色" name="#524e4d" style="background-color: rgb(82, 78, 77);">消炭色 #524e4d</color><color value="藍墨茶" name="#474a4d" style="background-color: rgb(71, 74, 77);">藍墨茶 #474a4d</color><color value="羊羹色" name="#383c3c" style="background-color: rgb(56, 60, 60);">羊羹色 #383c3c</color><color value="蝋色" name="#2b2b2b" style="background-color: rgb(43, 43, 43);">蝋色 #2b2b2b</color><color value="黒" name="#2b2b2b" style="background-color: rgb(43, 43, 43);">黒 #2b2b2b</color><color value="烏羽色" name="#180614" style="background-color: rgb(24, 6, 20);">烏羽色 #180614</color><color value="鉄黒" name="#281a14" style="background-color: rgb(40, 26, 20);">鉄黒 #281a14</color><color value="濡羽色" name="#000b00" style="background-color: rgb(0, 11, 0);">濡羽色 #000b00</color><color value="黒檀" name="#250d00" style="background-color: rgb(37, 13, 0);">黒檀 #250d00</color><color value="憲法黒茶" name="#241a08" style="background-color: rgb(36, 26, 8);">憲法黒茶 #241a08</color><color value="暗黒色" name="#16160e" style="background-color: rgb(22, 22, 14);">暗黒色 #16160e</color><color value="" name=""></color></colors>